Metadata-Version: 2.1
Name: drf-recaptcha-new
Version: 2.2.3
Summary: Django rest framework recaptcha field serializer.
Home-page: https://github.com/abhay033/drf-recaptcha.git
Author: Abhay Bhati
Author-email: abhaybhati987@gmail.com
License: MIT
Keywords: django,drf,rest,django-rest-framework,reCAPTCHA,reCAPTCHA v2,reCAPTCHA v3
Platform: UNKNOWN
Classifier: Development Status :: 5 - Production/Stable
Classifier: Environment :: Web Environment
Classifier: Environment :: Plugins
Classifier: Intended Audience :: Developers
Classifier: Framework :: Django
Classifier: Framework :: Django :: 3.2
Classifier: Framework :: Django :: 4.0
Classifier: Framework :: Django :: 4.1
Classifier: Intended Audience :: Developers
Classifier: License :: OSI Approved :: MIT License
Classifier: Operating System :: OS Independent
Classifier: Topic :: Internet :: WWW/HTTP :: Dynamic Content
Classifier: Topic :: Security
Classifier: Topic :: Software Development :: Libraries
Classifier: Programming Language :: Python
Classifier: Programming Language :: Python :: 3 :: Only
Classifier: Programming Language :: Python :: 3
Classifier: Programming Language :: Python :: 3.7
Classifier: Programming Language :: Python :: 3.8
Classifier: Programming Language :: Python :: 3.9
Classifier: Programming Language :: Python :: 3.10
Requires-Python: >=3.7
Requires-Dist: django (<4.2,>=3.2)
Requires-Dist: djangorestframework (<4.0,>=3.11)
Requires-Dist: django-ipware (<4.1,>=2.1)
